alibabacloud_tea_util_sse/__init__.py
alibabacloud_tea_util_sse/client.py
alibabacloud_tea_util_sse/models.py
alibabacloud_tea_util_sse-1.0.1.dist-info/METADATA
alibabacloud_tea_util_sse-1.0.1.dist-info/WHEEL
alibabacloud_tea_util_sse-1.0.1.dist-info/top_level.txt
alibabacloud_tea_util_sse-1.0.1.dist-info/RECORD
